README.md
setup.py
cn_tcp_server.egg-info/PKG-INFO
cn_tcp_server.egg-info/SOURCES.txt
cn_tcp_server.egg-info/dependency_links.txt
cn_tcp_server.egg-info/not-zip-safe
cn_tcp_server.egg-info/top_level.txt
tcp_chat/__init__.py
tcp_chat/__main__.py
tcp_chat/client/__init__.py
tcp_chat/client/client.py
tcp_chat/server/__init__.py
tcp_chat/server/bidict.py
tcp_chat/server/server.py