Metadata-Version: 2.1
Name: cn-tcp-server
Version: 0.0.1
Summary: Simple server and client for chatting
Home-page: https://github.com/cl1ckname/tcp_chat
Author-email: 20002mc@gmail.com
License: UNKNOWN
Platform: UNKNOWN
Classifier: Programming Language :: Python :: 3.6
